<?xml version="1.0" encoding="UTF-8"?>
<!DOCTYPE mapper PUBLIC "-//mybatis.org//DTD Mapper 3.0//EN" "http://mybatis.org/dtd/mybatis-3-mapper.dtd">
<mapper namespace="org.ehais.shop.mapper.tp.TpSuppliersMapper">
  <resultMap id="BaseResultMap" type="org.ehais.shop.model.tp.TpSuppliers">
    <!--
      WARNING - @mbg.generated
      This element is automatically generated by MyBatis Generator, do not modify.
      This element was generated on Sun Aug 06 21:16:43 CST 2017.
    -->
    <id column="suppliers_id" jdbcType="BIGINT" property="suppliersId" />
    <result column="user_id" jdbcType="BIGINT" property="userId" />
    <result column="openid" jdbcType="VARCHAR" property="openid" />
    <result column="suppliers_name" jdbcType="VARCHAR" property="suppliersName" />
    <result column="is_check" jdbcType="BIT" property="isCheck" />
    <result column="suppliers_contacts" jdbcType="VARCHAR" property="suppliersContacts" />
    <result column="suppliers_phone" jdbcType="VARCHAR" property="suppliersPhone" />
    <result column="suppliers_sn" jdbcType="VARCHAR" property="suppliersSn" />
    <result column="pic" jdbcType="VARCHAR" property="pic" />
    <result column="classify" jdbcType="VARCHAR" property="classify" />
  </resultMap>
  <resultMap extends="BaseResultMap" id="ResultMapWithBLOBs" type="org.ehais.shop.model.tp.TpSuppliers">
    <!--
      WARNING - @mbg.generated
      This element is automatically generated by MyBatis Generator, do not modify.
      This element was generated on Sun Aug 06 21:16:43 CST 2017.
    -->
    <result column="suppliers_desc" jdbcType="LONGVARCHAR" property="suppliersDesc" />
  </resultMap>
  <sql id="Example_Where_Clause">
    <!--
      WARNING - @mbg.generated
      This element is automatically generated by MyBatis Generator, do not modify.
      This element was generated on Sun Aug 06 21:16:43 CST 2017.
    -->
    <where>
      <foreach collection="oredCriteria" item="criteria" separator="or">
        <if test="criteria.valid">
          <trim prefix="(" prefixOverrides="and" suffix=")">
            <foreach collection="criteria.criteria" item="criterion">
              <choose>
                <when test="criterion.noValue">
                  and ${criterion.condition}
                </when>
                <when test="criterion.singleValue">
                  and ${criterion.condition} #{criterion.value}
                </when>
                <when test="criterion.betweenValue">
                  and ${criterion.condition} #{criterion.value} and #{criterion.secondValue}
                </when>
                <when test="criterion.listValue">
                  and ${criterion.condition}
                  <foreach close=")" collection="criterion.value" item="listItem" open="(" separator=",">
                    #{listItem}
                  </foreach>
                </when>
              </choose>
            </foreach>
          </trim>
        </if>
      </foreach>
    </where>
  </sql>
  <sql id="Update_By_Example_Where_Clause">
    <!--
      WARNING - @mbg.generated
      This element is automatically generated by MyBatis Generator, do not modify.
      This element was generated on Sun Aug 06 21:16:43 CST 2017.
    -->
    <where>
      <foreach collection="example.oredCriteria" item="criteria" separator="or">
        <if test="criteria.valid">
          <trim prefix="(" prefixOverrides="and" suffix=")">
            <foreach collection="criteria.criteria" item="criterion">
              <choose>
                <when test="criterion.noValue">
                  and ${criterion.condition}
                </when>
                <when test="criterion.singleValue">
                  and ${criterion.condition} #{criterion.value}
                </when>
                <when test="criterion.betweenValue">
                  and ${criterion.condition} #{criterion.value} and #{criterion.secondValue}
                </when>
                <when test="criterion.listValue">
                  and ${criterion.condition}
                  <foreach close=")" collection="criterion.value" item="listItem" open="(" separator=",">
                    #{listItem}
                  </foreach>
                </when>
              </choose>
            </foreach>
          </trim>
        </if>
      </foreach>
    </where>
  </sql>
  <sql id="Base_Column_List">
    <!--
      WARNING - @mbg.generated
      This element is automatically generated by MyBatis Generator, do not modify.
      This element was generated on Sun Aug 06 21:16:43 CST 2017.
    -->
    suppliers_id, user_id, openid, suppliers_name, is_check, suppliers_contacts, suppliers_phone, 
    suppliers_sn, pic, classify
  </sql>
  <sql id="Blob_Column_List">
    <!--
      WARNING - @mbg.generated
      This element is automatically generated by MyBatis Generator, do not modify.
      This element was generated on Sun Aug 06 21:16:43 CST 2017.
    -->
    suppliers_desc
  </sql>
  <select id="selectByExampleWithBLOBs" parameterType="org.ehais.shop.model.tp.TpSuppliersExample" resultMap="ResultMapWithBLOBs">
    <!--
      WARNING - @mbg.generated
      This element is automatically generated by MyBatis Generator, do not modify.
      This element was generated on Sun Aug 06 21:16:43 CST 2017.
    -->
    select
    <if test="distinct">
      distinct
    </if>
    <include refid="Base_Column_List" />
    ,
    <include refid="Blob_Column_List" />
    from tp_suppliers
    <if test="_parameter != null">
      <include refid="Example_Where_Clause" />
    </if>
    <if test="orderByClause != null">
      order by ${orderByClause}
    </if>
    <if test="limitStart >= 0 and limitEnd > 0">
       limit ${limitStart} , ${limitEnd}
    </if>
  </select>
  <select id="selectByExample" parameterType="org.ehais.shop.model.tp.TpSuppliersExample" resultMap="BaseResultMap">
    <!--
      WARNING - @mbg.generated
      This element is automatically generated by MyBatis Generator, do not modify.
      This element was generated on Sun Aug 06 21:16:43 CST 2017.
    -->
    select
    <if test="distinct">
      distinct
    </if>
    <include refid="Base_Column_List" />
    from tp_suppliers
    <if test="_parameter != null">
      <include refid="Example_Where_Clause" />
    </if>
    <if test="orderByClause != null">
      order by ${orderByClause}
    </if>
    <if test="limitStart >= 0 and limitEnd > 0">
       limit ${limitStart} , ${limitEnd}
    </if>
  </select>
  <select id="selectByPrimaryKey" parameterType="java.lang.Long" resultMap="ResultMapWithBLOBs">
    <!--
      WARNING - @mbg.generated
      This element is automatically generated by MyBatis Generator, do not modify.
      This element was generated on Sun Aug 06 21:16:43 CST 2017.
    -->
    select 
    <include refid="Base_Column_List" />
    ,
    <include refid="Blob_Column_List" />
    from tp_suppliers
    where suppliers_id = #{suppliersId,jdbcType=BIGINT}
  </select>
  <delete id="deleteByPrimaryKey" parameterType="java.lang.Long">
    <!--
      WARNING - @mbg.generated
      This element is automatically generated by MyBatis Generator, do not modify.
      This element was generated on Sun Aug 06 21:16:43 CST 2017.
    -->
    delete from tp_suppliers
    where suppliers_id = #{suppliersId,jdbcType=BIGINT}
  </delete>
  <delete id="deleteByExample" parameterType="org.ehais.shop.model.tp.TpSuppliersExample">
    <!--
      WARNING - @mbg.generated
      This element is automatically generated by MyBatis Generator, do not modify.
      This element was generated on Sun Aug 06 21:16:43 CST 2017.
    -->
    delete from tp_suppliers
    <if test="_parameter != null">
      <include refid="Example_Where_Clause" />
    </if>
  </delete>
  <insert id="insert" parameterType="org.ehais.shop.model.tp.TpSuppliers">
    <!--
      WARNING - @mbg.generated
      This element is automatically generated by MyBatis Generator, do not modify.
      This element was generated on Sun Aug 06 21:16:43 CST 2017.
    -->
    <selectKey keyProperty="suppliersId" order="AFTER" resultType="java.lang.Long">
      SELECT LAST_INSERT_ID()
    </selectKey>
    insert into tp_suppliers (user_id, openid, suppliers_name, 
      is_check, suppliers_contacts, suppliers_phone, 
      suppliers_sn, pic, classify, 
      suppliers_desc)
    values (#{userId,jdbcType=BIGINT}, #{openid,jdbcType=VARCHAR}, #{suppliersName,jdbcType=VARCHAR}, 
      #{isCheck,jdbcType=BIT}, #{suppliersContacts,jdbcType=VARCHAR}, #{suppliersPhone,jdbcType=VARCHAR}, 
      #{suppliersSn,jdbcType=VARCHAR}, #{pic,jdbcType=VARCHAR}, #{classify,jdbcType=VARCHAR}, 
      #{suppliersDesc,jdbcType=LONGVARCHAR})
  </insert>
  <insert id="insertSelective" parameterType="org.ehais.shop.model.tp.TpSuppliers">
    <!--
      WARNING - @mbg.generated
      This element is automatically generated by MyBatis Generator, do not modify.
      This element was generated on Sun Aug 06 21:16:43 CST 2017.
    -->
    <selectKey keyProperty="suppliersId" order="AFTER" resultType="java.lang.Long">
      SELECT LAST_INSERT_ID()
    </selectKey>
    insert into tp_suppliers
    <trim prefix="(" suffix=")" suffixOverrides=",">
      <if test="userId != null">
        user_id,
      </if>
      <if test="openid != null">
        openid,
      </if>
      <if test="suppliersName != null">
        suppliers_name,
      </if>
      <if test="isCheck != null">
        is_check,
      </if>
      <if test="suppliersContacts != null">
        suppliers_contacts,
      </if>
      <if test="suppliersPhone != null">
        suppliers_phone,
      </if>
      <if test="suppliersSn != null">
        suppliers_sn,
      </if>
      <if test="pic != null">
        pic,
      </if>
      <if test="classify != null">
        classify,
      </if>
      <if test="suppliersDesc != null">
        suppliers_desc,
      </if>
    </trim>
    <trim prefix="values (" suffix=")" suffixOverrides=",">
      <if test="userId != null">
        #{userId,jdbcType=BIGINT},
      </if>
      <if test="openid != null">
        #{openid,jdbcType=VARCHAR},
      </if>
      <if test="suppliersName != null">
        #{suppliersName,jdbcType=VARCHAR},
      </if>
      <if test="isCheck != null">
        #{isCheck,jdbcType=BIT},
      </if>
      <if test="suppliersContacts != null">
        #{suppliersContacts,jdbcType=VARCHAR},
      </if>
      <if test="suppliersPhone != null">
        #{suppliersPhone,jdbcType=VARCHAR},
      </if>
      <if test="suppliersSn != null">
        #{suppliersSn,jdbcType=VARCHAR},
      </if>
      <if test="pic != null">
        #{pic,jdbcType=VARCHAR},
      </if>
      <if test="classify != null">
        #{classify,jdbcType=VARCHAR},
      </if>
      <if test="suppliersDesc != null">
        #{suppliersDesc,jdbcType=LONGVARCHAR},
      </if>
    </trim>
  </insert>
  <select id="countByExample" parameterType="org.ehais.shop.model.tp.TpSuppliersExample" resultType="java.lang.Long">
    <!--
      WARNING - @mbg.generated
      This element is automatically generated by MyBatis Generator, do not modify.
      This element was generated on Sun Aug 06 21:16:43 CST 2017.
    -->
    select count(*) from tp_suppliers
    <if test="_parameter != null">
      <include refid="Example_Where_Clause" />
    </if>
  </select>
  <update id="updateByExampleSelective" parameterType="map">
    <!--
      WARNING - @mbg.generated
      This element is automatically generated by MyBatis Generator, do not modify.
      This element was generated on Sun Aug 06 21:16:43 CST 2017.
    -->
    update tp_suppliers
    <set>
      <if test="record.suppliersId != null">
        suppliers_id = #{record.suppliersId,jdbcType=BIGINT},
      </if>
      <if test="record.userId != null">
        user_id = #{record.userId,jdbcType=BIGINT},
      </if>
      <if test="record.openid != null">
        openid = #{record.openid,jdbcType=VARCHAR},
      </if>
      <if test="record.suppliersName != null">
        suppliers_name = #{record.suppliersName,jdbcType=VARCHAR},
      </if>
      <if test="record.isCheck != null">
        is_check = #{record.isCheck,jdbcType=BIT},
      </if>
      <if test="record.suppliersContacts != null">
        suppliers_contacts = #{record.suppliersContacts,jdbcType=VARCHAR},
      </if>
      <if test="record.suppliersPhone != null">
        suppliers_phone = #{record.suppliersPhone,jdbcType=VARCHAR},
      </if>
      <if test="record.suppliersSn != null">
        suppliers_sn = #{record.suppliersSn,jdbcType=VARCHAR},
      </if>
      <if test="record.pic != null">
        pic = #{record.pic,jdbcType=VARCHAR},
      </if>
      <if test="record.classify != null">
        classify = #{record.classify,jdbcType=VARCHAR},
      </if>
      <if test="record.suppliersDesc != null">
        suppliers_desc = #{record.suppliersDesc,jdbcType=LONGVARCHAR},
      </if>
    </set>
    <if test="_parameter != null">
      <include refid="Update_By_Example_Where_Clause" />
    </if>
  </update>
  <update id="updateByExampleWithBLOBs" parameterType="map">
    <!--
      WARNING - @mbg.generated
      This element is automatically generated by MyBatis Generator, do not modify.
      This element was generated on Sun Aug 06 21:16:43 CST 2017.
    -->
    update tp_suppliers
    set suppliers_id = #{record.suppliersId,jdbcType=BIGINT},
      user_id = #{record.userId,jdbcType=BIGINT},
      openid = #{record.openid,jdbcType=VARCHAR},
      suppliers_name = #{record.suppliersName,jdbcType=VARCHAR},
      is_check = #{record.isCheck,jdbcType=BIT},
      suppliers_contacts = #{record.suppliersContacts,jdbcType=VARCHAR},
      suppliers_phone = #{record.suppliersPhone,jdbcType=VARCHAR},
      suppliers_sn = #{record.suppliersSn,jdbcType=VARCHAR},
      pic = #{record.pic,jdbcType=VARCHAR},
      classify = #{record.classify,jdbcType=VARCHAR},
      suppliers_desc = #{record.suppliersDesc,jdbcType=LONGVARCHAR}
    <if test="_parameter != null">
      <include refid="Update_By_Example_Where_Clause" />
    </if>
  </update>
  <update id="updateByExample" parameterType="map">
    <!--
      WARNING - @mbg.generated
      This element is automatically generated by MyBatis Generator, do not modify.
      This element was generated on Sun Aug 06 21:16:43 CST 2017.
    -->
    update tp_suppliers
    set suppliers_id = #{record.suppliersId,jdbcType=BIGINT},
      user_id = #{record.userId,jdbcType=BIGINT},
      openid = #{record.openid,jdbcType=VARCHAR},
      suppliers_name = #{record.suppliersName,jdbcType=VARCHAR},
      is_check = #{record.isCheck,jdbcType=BIT},
      suppliers_contacts = #{record.suppliersContacts,jdbcType=VARCHAR},
      suppliers_phone = #{record.suppliersPhone,jdbcType=VARCHAR},
      suppliers_sn = #{record.suppliersSn,jdbcType=VARCHAR},
      pic = #{record.pic,jdbcType=VARCHAR},
      classify = #{record.classify,jdbcType=VARCHAR}
    <if test="_parameter != null">
      <include refid="Update_By_Example_Where_Clause" />
    </if>
  </update>
  <update id="updateByPrimaryKeySelective" parameterType="org.ehais.shop.model.tp.TpSuppliers">
    <!--
      WARNING - @mbg.generated
      This element is automatically generated by MyBatis Generator, do not modify.
      This element was generated on Sun Aug 06 21:16:43 CST 2017.
    -->
    update tp_suppliers
    <set>
      <if test="userId != null">
        user_id = #{userId,jdbcType=BIGINT},
      </if>
      <if test="openid != null">
        openid = #{openid,jdbcType=VARCHAR},
      </if>
      <if test="suppliersName != null">
        suppliers_name = #{suppliersName,jdbcType=VARCHAR},
      </if>
      <if test="isCheck != null">
        is_check = #{isCheck,jdbcType=BIT},
      </if>
      <if test="suppliersContacts != null">
        suppliers_contacts = #{suppliersContacts,jdbcType=VARCHAR},
      </if>
      <if test="suppliersPhone != null">
        suppliers_phone = #{suppliersPhone,jdbcType=VARCHAR},
      </if>
      <if test="suppliersSn != null">
        suppliers_sn = #{suppliersSn,jdbcType=VARCHAR},
      </if>
      <if test="pic != null">
        pic = #{pic,jdbcType=VARCHAR},
      </if>
      <if test="classify != null">
        classify = #{classify,jdbcType=VARCHAR},
      </if>
      <if test="suppliersDesc != null">
        suppliers_desc = #{suppliersDesc,jdbcType=LONGVARCHAR},
      </if>
    </set>
    where suppliers_id = #{suppliersId,jdbcType=BIGINT}
  </update>
  <update id="updateByPrimaryKeyWithBLOBs" parameterType="org.ehais.shop.model.tp.TpSuppliers">
    <!--
      WARNING - @mbg.generated
      This element is automatically generated by MyBatis Generator, do not modify.
      This element was generated on Sun Aug 06 21:16:43 CST 2017.
    -->
    update tp_suppliers
    set user_id = #{userId,jdbcType=BIGINT},
      openid = #{openid,jdbcType=VARCHAR},
      suppliers_name = #{suppliersName,jdbcType=VARCHAR},
      is_check = #{isCheck,jdbcType=BIT},
      suppliers_contacts = #{suppliersContacts,jdbcType=VARCHAR},
      suppliers_phone = #{suppliersPhone,jdbcType=VARCHAR},
      suppliers_sn = #{suppliersSn,jdbcType=VARCHAR},
      pic = #{pic,jdbcType=VARCHAR},
      classify = #{classify,jdbcType=VARCHAR},
      suppliers_desc = #{suppliersDesc,jdbcType=LONGVARCHAR}
    where suppliers_id = #{suppliersId,jdbcType=BIGINT}
  </update>
  <update id="updateByPrimaryKey" parameterType="org.ehais.shop.model.tp.TpSuppliers">
    <!--
      WARNING - @mbg.generated
      This element is automatically generated by MyBatis Generator, do not modify.
      This element was generated on Sun Aug 06 21:16:43 CST 2017.
    -->
    update tp_suppliers
    set user_id = #{userId,jdbcType=BIGINT},
      openid = #{openid,jdbcType=VARCHAR},
      suppliers_name = #{suppliersName,jdbcType=VARCHAR},
      is_check = #{isCheck,jdbcType=BIT},
      suppliers_contacts = #{suppliersContacts,jdbcType=VARCHAR},
      suppliers_phone = #{suppliersPhone,jdbcType=VARCHAR},
      suppliers_sn = #{suppliersSn,jdbcType=VARCHAR},
      pic = #{pic,jdbcType=VARCHAR},
      classify = #{classify,jdbcType=VARCHAR}
    where suppliers_id = #{suppliersId,jdbcType=BIGINT}
  </update>
</mapper>