<?xml version="1.0" encoding="UTF-8" ?>
<!DOCTYPE mapper PUBLIC "-//mybatis.org//DTD Mapper 3.0//EN" "http://mybatis.org/dtd/mybatis-3-mapper.dtd" >
<mapper namespace="org.ehais.project.mapper.ProIdeaMapper" >
  <resultMap id="BaseResultMap" type="org.ehais.project.model.ProIdea" >
    <!--
      WARNING - @mbggenerated
      This element is automatically generated by MyBatis Generator, do not modify.
      This element was generated on Thu Jan 07 21:35:26 CST 2016.
    -->
    <id column="idea_id" property="ideaId" jdbcType="INTEGER" />
    <result column="idea_title" property="ideaTitle" jdbcType="VARCHAR" />
    <result column="create_date" property="createDate" jdbcType="TIMESTAMP" />
    <result column="update_date" property="updateDate" jdbcType="TIMESTAMP" />
    <result column="user_id" property="userId" jdbcType="INTEGER" />
    <result column="state" property="state" jdbcType="INTEGER" />
    <result column="progress" property="progress" jdbcType="INTEGER" />
    <result column="plan_date" property="planDate" jdbcType="DATE" />
  </resultMap>
  <resultMap id="ResultMapWithBLOBs" type="org.ehais.project.model.ProIdeaWithBLOBs" extends="BaseResultMap" >
    <!--
      WARNING - @mbggenerated
      This element is automatically generated by MyBatis Generator, do not modify.
      This element was generated on Thu Jan 07 21:35:26 CST 2016.
    -->
    <result column="idea_content" property="ideaContent" jdbcType="LONGVARCHAR" />
    <result column="idea_m_content" property="ideaMContent" jdbcType="LONGVARCHAR" />
    <result column="idea_remark" property="ideaRemark" jdbcType="LONGVARCHAR" />
    <result column="idea_m_remark" property="ideaMRemark" jdbcType="LONGVARCHAR" />
    <result column="idea_m_plan" property="ideaMPlan" jdbcType="LONGVARCHAR" />
    <result column="idea_plan" property="ideaPlan" jdbcType="LONGVARCHAR" />
  </resultMap>
  <sql id="Example_Where_Clause" >
    <!--
      WARNING - @mbggenerated
      This element is automatically generated by MyBatis Generator, do not modify.
      This element was generated on Thu Jan 07 21:35:26 CST 2016.
    -->
    <where >
      <foreach collection="oredCriteria" item="criteria" separator="or" >
        <if test="criteria.valid" >
          <trim prefix="(" suffix=")" prefixOverrides="and" >
            <foreach collection="criteria.criteria" item="criterion" >
              <choose >
                <when test="criterion.noValue" >
                  and ${criterion.condition}
                </when>
                <when test="criterion.singleValue" >
                  and ${criterion.condition} #{criterion.value}
                </when>
                <when test="criterion.betweenValue" >
                  and ${criterion.condition} #{criterion.value} and #{criterion.secondValue}
                </when>
                <when test="criterion.listValue" >
                  and ${criterion.condition}
                  <foreach collection="criterion.value" item="listItem" open="(" close=")" separator="," >
                    #{listItem}
                  </foreach>
                </when>
              </choose>
            </foreach>
          </trim>
        </if>
      </foreach>
    </where>
  </sql>
  <sql id="Update_By_Example_Where_Clause" >
    <!--
      WARNING - @mbggenerated
      This element is automatically generated by MyBatis Generator, do not modify.
      This element was generated on Thu Jan 07 21:35:26 CST 2016.
    -->
    <where >
      <foreach collection="example.oredCriteria" item="criteria" separator="or" >
        <if test="criteria.valid" >
          <trim prefix="(" suffix=")" prefixOverrides="and" >
            <foreach collection="criteria.criteria" item="criterion" >
              <choose >
                <when test="criterion.noValue" >
                  and ${criterion.condition}
                </when>
                <when test="criterion.singleValue" >
                  and ${criterion.condition} #{criterion.value}
                </when>
                <when test="criterion.betweenValue" >
                  and ${criterion.condition} #{criterion.value} and #{criterion.secondValue}
                </when>
                <when test="criterion.listValue" >
                  and ${criterion.condition}
                  <foreach collection="criterion.value" item="listItem" open="(" close=")" separator="," >
                    #{listItem}
                  </foreach>
                </when>
              </choose>
            </foreach>
          </trim>
        </if>
      </foreach>
    </where>
  </sql>
  <sql id="Base_Column_List" >
    <!--
      WARNING - @mbggenerated
      This element is automatically generated by MyBatis Generator, do not modify.
      This element was generated on Thu Jan 07 21:35:26 CST 2016.
    -->
    idea_id, idea_title, create_date, update_date, user_id, state, progress, plan_date
  </sql>
  <sql id="Blob_Column_List" >
    <!--
      WARNING - @mbggenerated
      This element is automatically generated by MyBatis Generator, do not modify.
      This element was generated on Thu Jan 07 21:35:26 CST 2016.
    -->
    idea_content, idea_m_content, idea_remark, idea_m_remark, idea_m_plan, idea_plan
  </sql>
  <select id="selectByExampleWithBLOBs" resultMap="ResultMapWithBLOBs" parameterType="org.ehais.project.model.ProIdeaExample" >
    <!--
      WARNING - @mbggenerated
      This element is automatically generated by MyBatis Generator, do not modify.
      This element was generated on Thu Jan 07 21:35:26 CST 2016.
    -->
    select
    <if test="distinct" >
      distinct
    </if>
    <include refid="Base_Column_List" />
    ,
    <include refid="Blob_Column_List" />
    from pro_idea
    <if test="_parameter != null" >
      <include refid="Example_Where_Clause" />
    </if>
    <if test="orderByClause != null" >
      order by ${orderByClause}
    </if>
  </select>
  <select id="selectByExample" resultMap="BaseResultMap" parameterType="org.ehais.project.model.ProIdeaExample" >
    <!--
      WARNING - @mbggenerated
      This element is automatically generated by MyBatis Generator, do not modify.
      This element was generated on Thu Jan 07 21:35:26 CST 2016.
    -->
    select
    <if test="distinct" >
      distinct
    </if>
    <include refid="Base_Column_List" />
    from pro_idea
    <if test="_parameter != null" >
      <include refid="Example_Where_Clause" />
    </if>
    <if test="orderByClause != null" >
      order by ${orderByClause}
    </if>
  </select>
  <select id="selectByPrimaryKey" resultMap="ResultMapWithBLOBs" parameterType="java.lang.Integer" >
    <!--
      WARNING - @mbggenerated
      This element is automatically generated by MyBatis Generator, do not modify.
      This element was generated on Thu Jan 07 21:35:26 CST 2016.
    -->
    select 
    <include refid="Base_Column_List" />
    ,
    <include refid="Blob_Column_List" />
    from pro_idea
    where idea_id = #{ideaId,jdbcType=INTEGER}
  </select>
  <delete id="deleteByPrimaryKey" parameterType="java.lang.Integer" >
    <!--
      WARNING - @mbggenerated
      This element is automatically generated by MyBatis Generator, do not modify.
      This element was generated on Thu Jan 07 21:35:26 CST 2016.
    -->
    delete from pro_idea
    where idea_id = #{ideaId,jdbcType=INTEGER}
  </delete>
  <delete id="deleteByExample" parameterType="org.ehais.project.model.ProIdeaExample" >
    <!--
      WARNING - @mbggenerated
      This element is automatically generated by MyBatis Generator, do not modify.
      This element was generated on Thu Jan 07 21:35:26 CST 2016.
    -->
    delete from pro_idea
    <if test="_parameter != null" >
      <include refid="Example_Where_Clause" />
    </if>
  </delete>
  <insert id="insert" parameterType="org.ehais.project.model.ProIdeaWithBLOBs" >
    <!--
      WARNING - @mbggenerated
      This element is automatically generated by MyBatis Generator, do not modify.
      This element was generated on Thu Jan 07 21:35:26 CST 2016.
    -->
    <selectKey resultType="java.lang.Integer" keyProperty="ideaId" order="AFTER" >
      SELECT LAST_INSERT_ID()
    </selectKey>
    insert into pro_idea (idea_title, create_date, update_date, 
      user_id, state, progress, 
      plan_date, idea_content, idea_m_content, 
      idea_remark, idea_m_remark, idea_m_plan, 
      idea_plan)
    values (#{ideaTitle,jdbcType=VARCHAR}, #{createDate,jdbcType=TIMESTAMP}, #{updateDate,jdbcType=TIMESTAMP}, 
      #{userId,jdbcType=INTEGER}, #{state,jdbcType=INTEGER}, #{progress,jdbcType=INTEGER}, 
      #{planDate,jdbcType=DATE}, #{ideaContent,jdbcType=LONGVARCHAR}, #{ideaMContent,jdbcType=LONGVARCHAR}, 
      #{ideaRemark,jdbcType=LONGVARCHAR}, #{ideaMRemark,jdbcType=LONGVARCHAR}, #{ideaMPlan,jdbcType=LONGVARCHAR}, 
      #{ideaPlan,jdbcType=LONGVARCHAR})
  </insert>
  <insert id="insertSelective" parameterType="org.ehais.project.model.ProIdeaWithBLOBs" >
    <!--
      WARNING - @mbggenerated
      This element is automatically generated by MyBatis Generator, do not modify.
      This element was generated on Thu Jan 07 21:35:26 CST 2016.
    -->
    <selectKey resultType="java.lang.Integer" keyProperty="ideaId" order="AFTER" >
      SELECT LAST_INSERT_ID()
    </selectKey>
    insert into pro_idea
    <trim prefix="(" suffix=")" suffixOverrides="," >
      <if test="ideaTitle != null" >
        idea_title,
      </if>
      <if test="createDate != null" >
        create_date,
      </if>
      <if test="updateDate != null" >
        update_date,
      </if>
      <if test="userId != null" >
        user_id,
      </if>
      <if test="state != null" >
        state,
      </if>
      <if test="progress != null" >
        progress,
      </if>
      <if test="planDate != null" >
        plan_date,
      </if>
      <if test="ideaContent != null" >
        idea_content,
      </if>
      <if test="ideaMContent != null" >
        idea_m_content,
      </if>
      <if test="ideaRemark != null" >
        idea_remark,
      </if>
      <if test="ideaMRemark != null" >
        idea_m_remark,
      </if>
      <if test="ideaMPlan != null" >
        idea_m_plan,
      </if>
      <if test="ideaPlan != null" >
        idea_plan,
      </if>
    </trim>
    <trim prefix="values (" suffix=")" suffixOverrides="," >
      <if test="ideaTitle != null" >
        #{ideaTitle,jdbcType=VARCHAR},
      </if>
      <if test="createDate != null" >
        #{createDate,jdbcType=TIMESTAMP},
      </if>
      <if test="updateDate != null" >
        #{updateDate,jdbcType=TIMESTAMP},
      </if>
      <if test="userId != null" >
        #{userId,jdbcType=INTEGER},
      </if>
      <if test="state != null" >
        #{state,jdbcType=INTEGER},
      </if>
      <if test="progress != null" >
        #{progress,jdbcType=INTEGER},
      </if>
      <if test="planDate != null" >
        #{planDate,jdbcType=DATE},
      </if>
      <if test="ideaContent != null" >
        #{ideaContent,jdbcType=LONGVARCHAR},
      </if>
      <if test="ideaMContent != null" >
        #{ideaMContent,jdbcType=LONGVARCHAR},
      </if>
      <if test="ideaRemark != null" >
        #{ideaRemark,jdbcType=LONGVARCHAR},
      </if>
      <if test="ideaMRemark != null" >
        #{ideaMRemark,jdbcType=LONGVARCHAR},
      </if>
      <if test="ideaMPlan != null" >
        #{ideaMPlan,jdbcType=LONGVARCHAR},
      </if>
      <if test="ideaPlan != null" >
        #{ideaPlan,jdbcType=LONGVARCHAR},
      </if>
    </trim>
  </insert>
  <select id="countByExample" parameterType="org.ehais.project.model.ProIdeaExample" resultType="java.lang.Integer" >
    <!--
      WARNING - @mbggenerated
      This element is automatically generated by MyBatis Generator, do not modify.
      This element was generated on Thu Jan 07 21:35:26 CST 2016.
    -->
    select count(*) from pro_idea
    <if test="_parameter != null" >
      <include refid="Example_Where_Clause" />
    </if>
  </select>
  <update id="updateByExampleSelective" parameterType="map" >
    <!--
      WARNING - @mbggenerated
      This element is automatically generated by MyBatis Generator, do not modify.
      This element was generated on Thu Jan 07 21:35:26 CST 2016.
    -->
    update pro_idea
    <set >
      <if test="record.ideaId != null" >
        idea_id = #{record.ideaId,jdbcType=INTEGER},
      </if>
      <if test="record.ideaTitle != null" >
        idea_title = #{record.ideaTitle,jdbcType=VARCHAR},
      </if>
      <if test="record.createDate != null" >
        create_date = #{record.createDate,jdbcType=TIMESTAMP},
      </if>
      <if test="record.updateDate != null" >
        update_date = #{record.updateDate,jdbcType=TIMESTAMP},
      </if>
      <if test="record.userId != null" >
        user_id = #{record.userId,jdbcType=INTEGER},
      </if>
      <if test="record.state != null" >
        state = #{record.state,jdbcType=INTEGER},
      </if>
      <if test="record.progress != null" >
        progress = #{record.progress,jdbcType=INTEGER},
      </if>
      <if test="record.planDate != null" >
        plan_date = #{record.planDate,jdbcType=DATE},
      </if>
      <if test="record.ideaContent != null" >
        idea_content = #{record.ideaContent,jdbcType=LONGVARCHAR},
      </if>
      <if test="record.ideaMContent != null" >
        idea_m_content = #{record.ideaMContent,jdbcType=LONGVARCHAR},
      </if>
      <if test="record.ideaRemark != null" >
        idea_remark = #{record.ideaRemark,jdbcType=LONGVARCHAR},
      </if>
      <if test="record.ideaMRemark != null" >
        idea_m_remark = #{record.ideaMRemark,jdbcType=LONGVARCHAR},
      </if>
      <if test="record.ideaMPlan != null" >
        idea_m_plan = #{record.ideaMPlan,jdbcType=LONGVARCHAR},
      </if>
      <if test="record.ideaPlan != null" >
        idea_plan = #{record.ideaPlan,jdbcType=LONGVARCHAR},
      </if>
    </set>
    <if test="_parameter != null" >
      <include refid="Update_By_Example_Where_Clause" />
    </if>
  </update>
  <update id="updateByExampleWithBLOBs" parameterType="map" >
    <!--
      WARNING - @mbggenerated
      This element is automatically generated by MyBatis Generator, do not modify.
      This element was generated on Thu Jan 07 21:35:26 CST 2016.
    -->
    update pro_idea
    set idea_id = #{record.ideaId,jdbcType=INTEGER},
      idea_title = #{record.ideaTitle,jdbcType=VARCHAR},
      create_date = #{record.createDate,jdbcType=TIMESTAMP},
      update_date = #{record.updateDate,jdbcType=TIMESTAMP},
      user_id = #{record.userId,jdbcType=INTEGER},
      state = #{record.state,jdbcType=INTEGER},
      progress = #{record.progress,jdbcType=INTEGER},
      plan_date = #{record.planDate,jdbcType=DATE},
      idea_content = #{record.ideaContent,jdbcType=LONGVARCHAR},
      idea_m_content = #{record.ideaMContent,jdbcType=LONGVARCHAR},
      idea_remark = #{record.ideaRemark,jdbcType=LONGVARCHAR},
      idea_m_remark = #{record.ideaMRemark,jdbcType=LONGVARCHAR},
      idea_m_plan = #{record.ideaMPlan,jdbcType=LONGVARCHAR},
      idea_plan = #{record.ideaPlan,jdbcType=LONGVARCHAR}
    <if test="_parameter != null" >
      <include refid="Update_By_Example_Where_Clause" />
    </if>
  </update>
  <update id="updateByExample" parameterType="map" >
    <!--
      WARNING - @mbggenerated
      This element is automatically generated by MyBatis Generator, do not modify.
      This element was generated on Thu Jan 07 21:35:26 CST 2016.
    -->
    update pro_idea
    set idea_id = #{record.ideaId,jdbcType=INTEGER},
      idea_title = #{record.ideaTitle,jdbcType=VARCHAR},
      create_date = #{record.createDate,jdbcType=TIMESTAMP},
      update_date = #{record.updateDate,jdbcType=TIMESTAMP},
      user_id = #{record.userId,jdbcType=INTEGER},
      state = #{record.state,jdbcType=INTEGER},
      progress = #{record.progress,jdbcType=INTEGER},
      plan_date = #{record.planDate,jdbcType=DATE}
    <if test="_parameter != null" >
      <include refid="Update_By_Example_Where_Clause" />
    </if>
  </update>
  <update id="updateByPrimaryKeySelective" parameterType="org.ehais.project.model.ProIdeaWithBLOBs" >
    <!--
      WARNING - @mbggenerated
      This element is automatically generated by MyBatis Generator, do not modify.
      This element was generated on Thu Jan 07 21:35:26 CST 2016.
    -->
    update pro_idea
    <set >
      <if test="ideaTitle != null" >
        idea_title = #{ideaTitle,jdbcType=VARCHAR},
      </if>
      <if test="createDate != null" >
        create_date = #{createDate,jdbcType=TIMESTAMP},
      </if>
      <if test="updateDate != null" >
        update_date = #{updateDate,jdbcType=TIMESTAMP},
      </if>
      <if test="userId != null" >
        user_id = #{userId,jdbcType=INTEGER},
      </if>
      <if test="state != null" >
        state = #{state,jdbcType=INTEGER},
      </if>
      <if test="progress != null" >
        progress = #{progress,jdbcType=INTEGER},
      </if>
      <if test="planDate != null" >
        plan_date = #{planDate,jdbcType=DATE},
      </if>
      <if test="ideaContent != null" >
        idea_content = #{ideaContent,jdbcType=LONGVARCHAR},
      </if>
      <if test="ideaMContent != null" >
        idea_m_content = #{ideaMContent,jdbcType=LONGVARCHAR},
      </if>
      <if test="ideaRemark != null" >
        idea_remark = #{ideaRemark,jdbcType=LONGVARCHAR},
      </if>
      <if test="ideaMRemark != null" >
        idea_m_remark = #{ideaMRemark,jdbcType=LONGVARCHAR},
      </if>
      <if test="ideaMPlan != null" >
        idea_m_plan = #{ideaMPlan,jdbcType=LONGVARCHAR},
      </if>
      <if test="ideaPlan != null" >
        idea_plan = #{ideaPlan,jdbcType=LONGVARCHAR},
      </if>
    </set>
    where idea_id = #{ideaId,jdbcType=INTEGER}
  </update>
  <update id="updateByPrimaryKeyWithBLOBs" parameterType="org.ehais.project.model.ProIdeaWithBLOBs" >
    <!--
      WARNING - @mbggenerated
      This element is automatically generated by MyBatis Generator, do not modify.
      This element was generated on Thu Jan 07 21:35:26 CST 2016.
    -->
    update pro_idea
    set idea_title = #{ideaTitle,jdbcType=VARCHAR},
      create_date = #{createDate,jdbcType=TIMESTAMP},
      update_date = #{updateDate,jdbcType=TIMESTAMP},
      user_id = #{userId,jdbcType=INTEGER},
      state = #{state,jdbcType=INTEGER},
      progress = #{progress,jdbcType=INTEGER},
      plan_date = #{planDate,jdbcType=DATE},
      idea_content = #{ideaContent,jdbcType=LONGVARCHAR},
      idea_m_content = #{ideaMContent,jdbcType=LONGVARCHAR},
      idea_remark = #{ideaRemark,jdbcType=LONGVARCHAR},
      idea_m_remark = #{ideaMRemark,jdbcType=LONGVARCHAR},
      idea_m_plan = #{ideaMPlan,jdbcType=LONGVARCHAR},
      idea_plan = #{ideaPlan,jdbcType=LONGVARCHAR}
    where idea_id = #{ideaId,jdbcType=INTEGER}
  </update>
  <update id="updateByPrimaryKey" parameterType="org.ehais.project.model.ProIdea" >
    <!--
      WARNING - @mbggenerated
      This element is automatically generated by MyBatis Generator, do not modify.
      This element was generated on Thu Jan 07 21:35:26 CST 2016.
    -->
    update pro_idea
    set idea_title = #{ideaTitle,jdbcType=VARCHAR},
      create_date = #{createDate,jdbcType=TIMESTAMP},
      update_date = #{updateDate,jdbcType=TIMESTAMP},
      user_id = #{userId,jdbcType=INTEGER},
      state = #{state,jdbcType=INTEGER},
      progress = #{progress,jdbcType=INTEGER},
      plan_date = #{planDate,jdbcType=DATE}
    where idea_id = #{ideaId,jdbcType=INTEGER}
  </update>
</mapper>